{
  "gitSyncId": "696f3687314f3f6f4b6b02eb_7975ba3e-bc1f-4345-aafb-95a285f448b2",
  "id": "Prospect Detail_ADDRESSING.subdistrict_ConvertToEN",
  "pluginId": "js-plugin",
  "pluginType": "JS",
  "unpublishedAction": {
    "actionConfiguration": {
      "encodeParamsToggle": true,
      "jsArguments": [
        {
          "name": "ID"
        }
      ],
      "paginationType": "NONE",
      "timeoutInMillisecond": 10000
    },
    "collectionId": "Prospect Detail_ADDRESSING",
    "confirmBeforeExecute": false,
    "datasource": {
      "isAutoGenerated": false,
      "name": "UNUSED_DATASOURCE",
      "pluginId": "js-plugin"
    },
    "dynamicBindingPathList": [
      {
        "key": "body"
      }
    ],
    "fullyQualifiedName": "ADDRESSING.subdistrict_ConvertToEN",
    "name": "subdistrict_ConvertToEN",
    "pageId": "Prospect Detail",
    "runBehaviour": "MANUAL",
    "userSetOnLoad": false
  }
}