{
  "animateLoading": true,
  "borderRadius": "{{appsmith.theme.borderRadius.appBorderRadius}}",
  "bottomRow": 11,
  "boxShadow": "none",
  "buttonColor": "green",
  "buttonVariant": "PRIMARY",
  "disabledWhenInvalid": false,
  "dynamicBindingPathList": [
    {
      "key": "borderRadius"
    }
  ],
  "dynamicTriggerPathList": [
    {
      "key": "onClick"
    }
  ],
  "isDefaultClickDisabled": true,
  "isDisabled": false,
  "isLoading": false,
  "isVisible": true,
  "key": "njmdz4xkxz",
  "leftColumn": 8,
  "minWidth": 120,
  "mobileBottomRow": 14,
  "mobileLeftColumn": 6,
  "mobileRightColumn": 22,
  "mobileTopRow": 10,
  "needsErrorInfo": false,
  "onClick": "{{JS.onUpdateStatus('Qualify', true);}}",
  "parentColumnSpace": 9.4375,
  "parentId": "sf3l1t5g5z",
  "parentRowSpace": 10,
  "placement": "CENTER",
  "recaptchaType": "V3",
  "renderMode": "CANVAS",
  "resetFormOnClick": false,
  "responsiveBehavior": "hug",
  "rightColumn": 24,
  "text": "Qualify",
  "topRow": 7,
  "type": "BUTTON_WIDGET",
  "version": 1,
  "widgetId": "r9g1zhax99",
  "widgetName": "BUTTON_QUALIFY_CONFIRM"
}