{
  "gitSyncId": "67e2786a166b1720655be9d3_7f62375c-ecaa-4dba-8f27-0a76bee93e6c",
  "id": "Manage Product Catalog_JS.onSaveConfirmClick",
  "pluginId": "js-plugin",
  "pluginType": "JS",
  "unpublishedAction": {
    "actionConfiguration": {
      "encodeParamsToggle": true,
      "jsArguments": [],
      "paginationType": "NONE",
      "timeoutInMillisecond": 10000
    },
    "collectionId": "Manage Product Catalog_JS",
    "confirmBeforeExecute": false,
    "datasource": {
      "isAutoGenerated": false,
      "name": "UNUSED_DATASOURCE",
      "pluginId": "js-plugin"
    },
    "dynamicBindingPathList": [
      {
        "key": "body"
      }
    ],
    "fullyQualifiedName": "JS.onSaveConfirmClick",
    "name": "onSaveConfirmClick",
    "pageId": "Manage Product Catalog",
    "runBehaviour": "MANUAL",
    "userSetOnLoad": false
  }
}