{
  "animateLoading": true,
  "borderRadius": "{{appsmith.theme.borderRadius.appBorderRadius}}",
  "bottomRow": 4,
  "boxShadow": "none",
  "buttonColor": "#fde047",
  "buttonVariant": "TERTIARY",
  "dynamicBindingPathList": [
    {
      "key": "borderRadius"
    }
  ],
  "dynamicTriggerPathList": [],
  "iconName": "warning-sign",
  "isDisabled": false,
  "isLoading": false,
  "isVisible": true,
  "key": "btih4h4bh1",
  "leftColumn": 1,
  "minWidth": 50,
  "mobileBottomRow": 4,
  "mobileLeftColumn": 1,
  "mobileRightColumn": 5,
  "mobileTopRow": 0,
  "needsErrorInfo": false,
  "parentColumnSpace": 7.5625,
  "parentId": "hyb7qktkmu",
  "parentRowSpace": 10,
  "renderMode": "CANVAS",
  "responsiveBehavior": "hug",
  "rightColumn": 5,
  "topRow": 0,
  "type": "ICON_BUTTON_WIDGET",
  "version": 1,
  "widgetId": "9caoq5t40v",
  "widgetName": "IconButton5"
}