{
  "gitSyncId": "696f3687314f3f6f4b6b02eb_79b6a090-b3e8-41ce-a9ce-dd78617a5102",
  "id": "Invoice Dashboard Copy_GlobalFunctions",
  "unpublishedCollection": {
    "name": "GlobalFunctions",
    "pageId": "Invoice Dashboard Copy",
    "pluginId": "js-plugin",
    "pluginType": "JS",
    "variables": [
      {
        "name": "V",
        "value": "4"
      },
      {
        "name": "LastChanged",
        "value": "\"if(!SELECT_FIELDS_VALIDATION.data) before run in init()\""
      }
    ]
  }
}