{
  "gitSyncId": "68e5e9a655eda7018e8c4294_c477271a-b711-4edf-abe4-08f546b959b0",
  "id": "Manage Company_JS.isArrayUndefinedOrEmpty",
  "pluginId": "js-plugin",
  "pluginType": "JS",
  "unpublishedAction": {
    "actionConfiguration": {
      "encodeParamsToggle": true,
      "jsArguments": [
        {
          "name": "array"
        }
      ],
      "paginationType": "NONE",
      "timeoutInMillisecond": 10000
    },
    "collectionId": "Manage Company_JS",
    "confirmBeforeExecute": false,
    "datasource": {
      "isAutoGenerated": false,
      "name": "UNUSED_DATASOURCE",
      "pluginId": "js-plugin"
    },
    "dynamicBindingPathList": [
      {
        "key": "body"
      }
    ],
    "fullyQualifiedName": "JS.isArrayUndefinedOrEmpty",
    "name": "isArrayUndefinedOrEmpty",
    "pageId": "Manage Company",
    "runBehaviour": "MANUAL",
    "userSetOnLoad": false
  }
}