{
  "gitSyncId": "696f3687314f3f6f4b6b02eb_be03aa11-0cfc-41f0-beff-2eac10d58957",
  "id": "Invoice Dashboard_Init.pageLoad",
  "pluginId": "js-plugin",
  "pluginType": "JS",
  "unpublishedAction": {
    "actionConfiguration": {
      "encodeParamsToggle": true,
      "jsArguments": [],
      "paginationType": "NONE",
      "timeoutInMillisecond": 10000
    },
    "collectionId": "Invoice Dashboard_Init",
    "confirmBeforeExecute": false,
    "datasource": {
      "isAutoGenerated": false,
      "name": "UNUSED_DATASOURCE",
      "pluginId": "js-plugin"
    },
    "dynamicBindingPathList": [
      {
        "key": "body"
      }
    ],
    "fullyQualifiedName": "Init.pageLoad",
    "name": "pageLoad",
    "pageId": "Invoice Dashboard",
    "runBehaviour": "ON_PAGE_LOAD",
    "userSetOnLoad": true
  }
}