{
  "gitSyncId": "67e2786a166b1720655be9d3_3c9c3777-6cde-4bd5-94f2-aa8e251ef9bd",
  "id": "Manage Product Inventory_JS.onClick_BUTTON_SEARCH",
  "pluginId": "js-plugin",
  "pluginType": "JS",
  "unpublishedAction": {
    "actionConfiguration": {
      "encodeParamsToggle": true,
      "jsArguments": [],
      "paginationType": "NONE",
      "timeoutInMillisecond": 10000
    },
    "collectionId": "Manage Product Inventory_JS",
    "confirmBeforeExecute": false,
    "datasource": {
      "isAutoGenerated": false,
      "name": "UNUSED_DATASOURCE",
      "pluginId": "js-plugin"
    },
    "dynamicBindingPathList": [
      {
        "key": "body"
      }
    ],
    "fullyQualifiedName": "JS.onClick_BUTTON_SEARCH",
    "name": "onClick_BUTTON_SEARCH",
    "pageId": "Manage Product Inventory",
    "runBehaviour": "MANUAL",
    "userSetOnLoad": false
  }
}