{
  "accentColor": "{{appsmith.theme.colors.primaryColor}}",
  "animateLoading": true,
  "borderColor": "#E0DEDE",
  "borderRadius": "{{appsmith.theme.borderRadius.appBorderRadius}}",
  "borderWidth": "1",
  "bottomRow": 44,
  "boxShadow": "{{appsmith.theme.boxShadow.appBoxShadow}}",
  "cachedTableData": {},
  "canFreezeColumn": true,
  "childStylesheet": {
    "button": {
      "borderRadius": "{{appsmith.theme.borderRadius.appBorderRadius}}",
      "boxShadow": "none",
      "buttonColor": "{{appsmith.theme.colors.primaryColor}}"
    },
    "editActions": {
      "discardBorderRadius": "{{appsmith.theme.borderRadius.appBorderRadius}}",
      "discardButtonColor": "{{appsmith.theme.colors.primaryColor}}",
      "saveBorderRadius": "{{appsmith.theme.borderRadius.appBorderRadius}}",
      "saveButtonColor": "{{appsmith.theme.colors.primaryColor}}"
    },
    "iconButton": {
      "borderRadius": "{{appsmith.theme.borderRadius.appBorderRadius}}",
      "boxShadow": "none",
      "buttonColor": "{{appsmith.theme.colors.primaryColor}}"
    },
    "menuButton": {
      "borderRadius": "{{appsmith.theme.borderRadius.appBorderRadius}}",
      "boxShadow": "none",
      "menuColor": "{{appsmith.theme.colors.primaryColor}}"
    }
  },
  "columnOrder": [
    "INVENTORY_ID",
    "INVENTORY_NAME",
    "PRODUCT_TYPE_TH",
    "FLOOR_NO",
    "TOTAL_RECORDS",
    "PRICE_PER_UNIT"
  ],
  "columnUpdatedAt": 1757315109063,
  "columnWidthMap": {
    "INVENTORY_NAME": 315
  },
  "customIsLoading": false,
  "customIsLoadingValue": "",
  "defaultPageSize": 0,
  "defaultSelectedRowIndex": 0,
  "defaultSelectedRowIndices": [
    0
  ],
  "delimiter": ",",
  "dynamicBindingPathList": [
    {
      "key": "accentColor"
    },
    {
      "key": "borderRadius"
    },
    {
      "key": "boxShadow"
    },
    {
      "key": "tableData"
    },
    {
      "key": "primaryColumns.INVENTORY_ID.computedValue"
    },
    {
      "key": "primaryColumns.INVENTORY_NAME.computedValue"
    },
    {
      "key": "primaryColumns.TOTAL_RECORDS.computedValue"
    },
    {
      "key": "primaryColumns.PRODUCT_TYPE_TH.computedValue"
    },
    {
      "key": "primaryColumns.FLOOR_NO.computedValue"
    },
    {
      "key": "primaryColumns.PRICE_PER_UNIT.computedValue"
    }
  ],
  "dynamicPropertyPathList": [
    {
      "key": "tableData"
    }
  ],
  "dynamicTriggerPathList": [],
  "enableClientSideSearch": true,
  "endOfData": false,
  "flexVerticalAlignment": "start",
  "horizontalAlignment": "LEFT",
  "inlineEditingSaveOption": "ROW_LEVEL",
  "isLoading": false,
  "isSortable": true,
  "isVisible": true,
  "isVisibleDownload": false,
  "isVisibleFilters": false,
  "isVisiblePagination": true,
  "isVisibleSearch": false,
  "key": "00euxq9y6i",
  "label": "Data",
  "leftColumn": 0,
  "minWidth": 450,
  "mobileBottomRow": 165,
  "mobileLeftColumn": 0,
  "mobileRightColumn": 12,
  "mobileTopRow": 137,
  "needsErrorInfo": false,
  "originalBottomRow": 165,
  "originalTopRow": 137,
  "parentColumnSpace": 23.390625,
  "parentId": "tnqz951xjp",
  "parentRowSpace": 10,
  "primaryColumnId": "INVENTORY_ID",
  "primaryColumns": {
    "FLOOR_NO": {
      "alias": "FLOOR_NO",
      "allowCellWrapping": false,
      "allowSameOptionsInNewRow": true,
      "cellBackground": "",
      "columnType": "text",
      "computedValue": "{{(() => { const tableData = TABLE_SearchForParentMeter.processedTableData || []; return tableData.length > 0 ? tableData.map((currentRow, currentIndex) => (currentRow[\"FLOOR_NO\"])) : FLOOR_NO })()}}",
      "currencyCode": "USD",
      "decimals": 0,
      "enableFilter": true,
      "enableSort": true,
      "fontStyle": "",
      "horizontalAlignment": "LEFT",
      "id": "FLOOR_NO",
      "index": 3,
      "isCellEditable": false,
      "isCellVisible": true,
      "isDerived": false,
      "isDisabled": false,
      "isDiscardVisible": true,
      "isEditable": false,
      "isSaveVisible": true,
      "isVisible": true,
      "label": "Floor",
      "notation": "standard",
      "originalId": "FLOOR_NO",
      "sticky": "",
      "textColor": "",
      "textSize": "0.875rem",
      "thousandSeparator": true,
      "validation": {},
      "verticalAlignment": "CENTER",
      "width": 150
    },
    "INVENTORY_ID": {
      "alias": "INVENTORY_ID",
      "allowCellWrapping": false,
      "allowSameOptionsInNewRow": true,
      "columnType": "text",
      "computedValue": "{{(() => { const tableData = TABLE_SearchForParentMeter.processedTableData || []; return tableData.length > 0 ? tableData.map((currentRow, currentIndex) => ( currentRow[\"INVENTORY_ID\"])) :  currentRow[\"INVENTORY_ID\"] })()}}",
      "currencyCode": "USD",
      "decimals": 0,
      "enableFilter": true,
      "enableSort": true,
      "horizontalAlignment": "LEFT",
      "id": "INVENTORY_ID",
      "index": 0,
      "isCellEditable": false,
      "isCellVisible": true,
      "isDerived": false,
      "isDisabled": false,
      "isDiscardVisible": true,
      "isEditable": false,
      "isSaveVisible": true,
      "isVisible": false,
      "label": "INVENTORY_ID",
      "notation": "standard",
      "originalId": "INVENTORY_ID",
      "sticky": "",
      "textSize": "0.875rem",
      "thousandSeparator": true,
      "validation": {},
      "verticalAlignment": "CENTER",
      "width": 150
    },
    "INVENTORY_NAME": {
      "alias": "INVENTORY_NAME",
      "allowCellWrapping": false,
      "allowSameOptionsInNewRow": true,
      "columnType": "text",
      "computedValue": "{{(() => { const tableData = TABLE_SearchForParentMeter.processedTableData || []; return tableData.length > 0 ? tableData.map((currentRow, currentIndex) => ( currentRow[\"INVENTORY_NAME\"])) :  currentRow[\"INVENTORY_NAME\"] })()}}",
      "currencyCode": "USD",
      "decimals": 0,
      "enableFilter": true,
      "enableSort": true,
      "horizontalAlignment": "LEFT",
      "id": "INVENTORY_NAME",
      "index": 1,
      "isCellEditable": false,
      "isCellVisible": true,
      "isDerived": false,
      "isDisabled": false,
      "isDiscardVisible": true,
      "isEditable": false,
      "isSaveVisible": true,
      "isVisible": true,
      "label": "Inventory Name",
      "notation": "standard",
      "originalId": "INVENTORY_NAME",
      "sticky": "",
      "textSize": "0.875rem",
      "thousandSeparator": true,
      "validation": {},
      "verticalAlignment": "CENTER",
      "width": 150
    },
    "PRICE_PER_UNIT": {
      "alias": "PRICE_PER_UNIT",
      "allowCellWrapping": false,
      "allowSameOptionsInNewRow": true,
      "cellBackground": "",
      "columnType": "number",
      "computedValue": "{{(() => { const tableData = TABLE_SearchForParentMeter.processedTableData || []; return tableData.length > 0 ? tableData.map((currentRow, currentIndex) => (currentRow[\"PRICE_PER_UNIT\"])) : PRICE_PER_UNIT })()}}",
      "currencyCode": "USD",
      "decimals": 0,
      "enableFilter": true,
      "enableSort": true,
      "fontStyle": "",
      "horizontalAlignment": "LEFT",
      "id": "PRICE_PER_UNIT",
      "index": 4,
      "isCellEditable": false,
      "isCellVisible": true,
      "isDerived": false,
      "isDisabled": false,
      "isDiscardVisible": true,
      "isEditable": false,
      "isSaveVisible": true,
      "isVisible": true,
      "label": "Price per unit",
      "notation": "standard",
      "originalId": "PRICE_PER_UNIT",
      "sticky": "",
      "textColor": "",
      "textSize": "0.875rem",
      "thousandSeparator": true,
      "validation": {},
      "verticalAlignment": "CENTER",
      "width": 150
    },
    "PRODUCT_TYPE_TH": {
      "alias": "PRODUCT_TYPE_TH",
      "allowCellWrapping": false,
      "allowSameOptionsInNewRow": true,
      "cellBackground": "",
      "columnType": "text",
      "computedValue": "{{(() => { const tableData = TABLE_SearchForParentMeter.processedTableData || []; return tableData.length > 0 ? tableData.map((currentRow, currentIndex) => (currentRow[\"PRODUCT_TYPE_TH\"])) : PRODUCT_TYPE_TH })()}}",
      "currencyCode": "USD",
      "decimals": 0,
      "enableFilter": true,
      "enableSort": true,
      "fontStyle": "",
      "horizontalAlignment": "LEFT",
      "id": "PRODUCT_TYPE_TH",
      "index": 2,
      "isCellEditable": false,
      "isCellVisible": true,
      "isDerived": false,
      "isDisabled": false,
      "isDiscardVisible": true,
      "isEditable": false,
      "isSaveVisible": true,
      "isVisible": true,
      "label": "Type",
      "notation": "standard",
      "originalId": "PRODUCT_TYPE_TH",
      "sticky": "",
      "textColor": "",
      "textSize": "0.875rem",
      "thousandSeparator": true,
      "validation": {},
      "verticalAlignment": "CENTER",
      "width": 150
    },
    "TOTAL_RECORDS": {
      "alias": "TOTAL_RECORDS",
      "allowCellWrapping": false,
      "allowSameOptionsInNewRow": true,
      "columnType": "number",
      "computedValue": "{{(() => { const tableData = TABLE_SearchForParentMeter.processedTableData || []; return tableData.length > 0 ? tableData.map((currentRow, currentIndex) => ( currentRow[\"TOTAL_RECORDS\"])) :  currentRow[\"TOTAL_RECORDS\"] })()}}",
      "currencyCode": "USD",
      "decimals": 0,
      "enableFilter": true,
      "enableSort": true,
      "horizontalAlignment": "LEFT",
      "id": "TOTAL_RECORDS",
      "index": 2,
      "isCellEditable": false,
      "isCellVisible": true,
      "isDerived": false,
      "isDisabled": false,
      "isDiscardVisible": true,
      "isEditable": false,
      "isSaveVisible": true,
      "isVisible": false,
      "label": "TOTAL_RECORDS",
      "notation": "standard",
      "originalId": "TOTAL_RECORDS",
      "sticky": "",
      "textSize": "0.875rem",
      "thousandSeparator": true,
      "validation": {},
      "verticalAlignment": "CENTER",
      "width": 150
    }
  },
  "renderMode": "CANVAS",
  "responsiveBehavior": "fill",
  "rightColumn": 64,
  "searchKey": "",
  "tableData": "{{(_1_SP_SEARCH_FOR_PARENT_METER.data||Default_Table.parentMeters).filter(row=>row.TOTAL_RECORDS!=0)}}",
  "textSize": "0.875rem",
  "topRow": 16,
  "totalRecordsCount": 0,
  "type": "TABLE_WIDGET_V2",
  "version": 2,
  "verticalAlignment": "CENTER",
  "widgetId": "2r6jnh393x",
  "widgetName": "TABLE_SearchForParentMeter"
}