{
  "accentColor": "{{appsmith.theme.colors.primaryColor}}",
  "allowCurrencyChange": false,
  "animateLoading": true,
  "autoFocus": false,
  "borderRadius": "{{appsmith.theme.borderRadius.appBorderRadius}}",
  "bottomRow": 16,
  "boxShadow": "none",
  "decimals": 2,
  "defaultCurrencyCode": "THB",
  "defaultText": "{{PRICE_PER_UNIT.value ||\"\"}}",
  "dynamicBindingPathList": [
    {
      "key": "accentColor"
    },
    {
      "key": "borderRadius"
    },
    {
      "key": "defaultText"
    }
  ],
  "dynamicHeight": "AUTO_HEIGHT",
  "dynamicPropertyPathList": [
    {
      "key": "onTextChanged"
    }
  ],
  "dynamicTriggerPathList": [
    {
      "key": "onTextChanged"
    }
  ],
  "iconAlign": "left",
  "isDisabled": false,
  "isLoading": false,
  "isRequired": false,
  "isVisible": true,
  "key": "xffyrxb7pi",
  "label": "Price per unit",
  "labelAlignment": "left",
  "labelPosition": "Left",
  "labelStyle": "",
  "labelTextSize": "0.875rem",
  "labelWidth": "9",
  "leftColumn": 34,
  "maxDynamicHeight": 9000,
  "minDynamicHeight": 4,
  "minWidth": 450,
  "mobileBottomRow": 19,
  "mobileLeftColumn": 34,
  "mobileRightColumn": 54,
  "mobileTopRow": 12,
  "needsErrorInfo": false,
  "onTextChanged": "{{PRICE_PER_UNIT_Confirm.setValue(PRICE_PER_UNIT.value||\"\")}}",
  "originalBottomRow": 19,
  "originalTopRow": 12,
  "parentColumnSpace": 13.125,
  "parentId": "n6q6hthnd1",
  "parentRowSpace": 10,
  "renderMode": "CANVAS",
  "resetOnSubmit": true,
  "responsiveBehavior": "fill",
  "rightColumn": 63,
  "shouldScrollContents": true,
  "showStepArrows": false,
  "topRow": 12,
  "type": "CURRENCY_INPUT_WIDGET",
  "version": 1,
  "widgetId": "f2pcu9jq9c",
  "widgetName": "PRICE_PER_UNIT_Confirm"
}