{
  "gitSyncId": "696f3687314f3f6f4b6b02eb_c13ebfdd-cfda-4568-aa49-59064a4f36cc",
  "id": "Invoice Dashboard_Init.sessionCheck",
  "pluginId": "js-plugin",
  "pluginType": "JS",
  "unpublishedAction": {
    "actionConfiguration": {
      "encodeParamsToggle": true,
      "jsArguments": [],
      "paginationType": "NONE",
      "timeoutInMillisecond": 10000
    },
    "collectionId": "Invoice Dashboard_Init",
    "confirmBeforeExecute": false,
    "datasource": {
      "isAutoGenerated": false,
      "name": "UNUSED_DATASOURCE",
      "pluginId": "js-plugin"
    },
    "dynamicBindingPathList": [
      {
        "key": "body"
      }
    ],
    "fullyQualifiedName": "Init.sessionCheck",
    "name": "sessionCheck",
    "pageId": "Invoice Dashboard",
    "runBehaviour": "MANUAL",
    "userSetOnLoad": false
  }
}