{
  "animateLoading": true,
  "borderRadius": "{{appsmith.theme.borderRadius.appBorderRadius}}",
  "bottomRow": 20,
  "dynamicBindingPathList": [
    {
      "key": "truncateButtonColor"
    },
    {
      "key": "borderRadius"
    }
  ],
  "dynamicHeight": "FIXED",
  "dynamicTriggerPathList": [],
  "fontFamily": "Inter",
  "fontSize": "1.25rem",
  "fontStyle": "BOLD",
  "isLoading": false,
  "isVisible": true,
  "key": "veu9znmysv",
  "leftColumn": 0,
  "maxDynamicHeight": 9000,
  "minDynamicHeight": 4,
  "minWidth": 450,
  "mobileBottomRow": 4,
  "mobileLeftColumn": 0,
  "mobileRightColumn": 5,
  "mobileTopRow": 0,
  "needsErrorInfo": false,
  "originalBottomRow": 20,
  "originalTopRow": 16,
  "overflow": "NONE",
  "parentColumnSpace": 19.1875,
  "parentId": "o4iqjdusc4",
  "parentRowSpace": 10,
  "renderMode": "CANVAS",
  "responsiveBehavior": "fill",
  "rightColumn": 64,
  "shouldTruncate": false,
  "text": "Remark",
  "textAlign": "LEFT",
  "textColor": "#231F20",
  "topRow": 16,
  "truncateButtonColor": "{{appsmith.theme.colors.primaryColor}}",
  "type": "TEXT_WIDGET",
  "version": 1,
  "widgetId": "jl8ru4zheq",
  "widgetName": "Txt_Remark"
}