{
  "gitSyncId": "68cbc87355eda7018e8c32af_fa75bf2c-8b0e-4b99-98aa-2f2680c537c0",
  "id": "Receipt Detail_JS.onDeleteConfirmClick",
  "pluginId": "js-plugin",
  "pluginType": "JS",
  "unpublishedAction": {
    "actionConfiguration": {
      "encodeParamsToggle": true,
      "jsArguments": [],
      "paginationType": "NONE",
      "timeoutInMillisecond": 10000
    },
    "collectionId": "Receipt Detail_JS",
    "confirmBeforeExecute": false,
    "datasource": {
      "isAutoGenerated": false,
      "name": "UNUSED_DATASOURCE",
      "pluginId": "js-plugin"
    },
    "dynamicBindingPathList": [
      {
        "key": "body"
      }
    ],
    "fullyQualifiedName": "JS.onDeleteConfirmClick",
    "name": "onDeleteConfirmClick",
    "pageId": "Receipt Detail",
    "runBehaviour": "MANUAL",
    "userSetOnLoad": false
  }
}