{
  "accentColor": "{{appsmith.theme.colors.primaryColor}}",
  "animateLoading": true,
  "borderRadius": "{{appsmith.theme.borderRadius.appBorderRadius}}",
  "bottomRow": 15,
  "boxShadow": "none",
  "defaultOptionValue": "GREEN",
  "dynamicBindingPathList": [
    {
      "key": "accentColor"
    },
    {
      "key": "borderRadius"
    }
  ],
  "dynamicHeight": "AUTO_HEIGHT",
  "dynamicPropertyPathList": [
    {
      "key": "sourceData"
    }
  ],
  "dynamicTriggerPathList": [],
  "isDisabled": false,
  "isFilterable": true,
  "isLoading": false,
  "isRequired": false,
  "isVisible": true,
  "key": "72xnnx6qo8",
  "labelAlignment": "left",
  "labelPosition": "Left",
  "labelText": "Floor Required",
  "labelTextSize": "1rem",
  "labelWidth": "12",
  "leftColumn": 35,
  "maxDynamicHeight": 9000,
  "minDynamicHeight": 4,
  "minWidth": 450,
  "mobileBottomRow": 26,
  "mobileLeftColumn": 35,
  "mobileRightColumn": 55,
  "mobileTopRow": 19,
  "needsErrorInfo": false,
  "optionLabel": "name",
  "optionValue": "code",
  "originalBottomRow": 14,
  "originalTopRow": 10,
  "parentColumnSpace": 19.5,
  "parentId": "gxo76kmw4r",
  "parentRowSpace": 10,
  "placeholderText": "Select option",
  "renderMode": "CANVAS",
  "responsiveBehavior": "fill",
  "rightColumn": 63,
  "serverSideFiltering": false,
  "shouldScrollContents": true,
  "sourceData": "[  {\n    \"name\": \"Not specific\",\n    \"code\": \"Not specific\"\n  },\n  {\n    \"name\": \"FL. 2-10\",\n    \"code\": \"FL. 2-10\"\n  },\n  {\n    \"name\": \"FL. 11-18\",\n    \"code\": \"FL. 11-18\"\n  },\n    {\n    \"name\": \"FL.19-26\",\n    \"code\": \"FL.19-26\"\n  },\n    {\n    \"name\": \"FL.27-37\",\n    \"code\": \"FL.127-37\"\n  }\n]",
  "topRow": 11,
  "type": "SELECT_WIDGET",
  "version": 1,
  "widgetId": "nu5l81ft11",
  "widgetName": "FLOOR_REQUIRED"
}